AUTHORS
LICENSE
MANIFEST.in
README.rst
setup.py
src/eukalypse_now/__init__.py
src/eukalypse_now/admin.py
src/eukalypse_now/context_processors.py
src/eukalypse_now/manage.py
src/eukalypse_now/models.py
src/eukalypse_now/settings.py
src/eukalypse_now/tasks.py
src/eukalypse_now/urls.py
src/eukalypse_now/views.py
src/eukalypse_now/wsgi.py
src/eukalypse_now.egg-info/PKG-INFO
src/eukalypse_now.egg-info/SOURCES.txt
src/eukalypse_now.egg-info/dependency_links.txt
src/eukalypse_now.egg-info/entry_points.txt
src/eukalypse_now.egg-info/not-zip-safe
src/eukalypse_now.egg-info/requires.txt
src/eukalypse_now.egg-info/top_level.txt
src/eukalypse_now/management/__init__.py
src/eukalypse_now/management/commands/__init__.py
src/eukalypse_now/management/commands/testrun.py
src/eukalypse_now/migrations/0001_initial.py
src/eukalypse_now/migrations/0002_auto__add_field_project_notify_mail__add_field_project_notify_only_err.py
src/eukalypse_now/migrations/0003_auto__add_field_project_active.py
src/eukalypse_now/migrations/0004_auto__add_field_test_wait.py
src/eukalypse_now/migrations/0005_auto__add_field_testresult_errorstate.py
src/eukalypse_now/migrations/0006_auto__del_field_testresult_errorstate__add_field_testresult_error_ackn.py
src/eukalypse_now/migrations/__init__.py
src/eukalypse_now/static/favicon.ico
src/eukalypse_now/static/admin/css/base.css
src/eukalypse_now/static/admin/css/changelists.css
src/eukalypse_now/static/admin/css/dashboard.css
src/eukalypse_now/static/admin/css/forms.css
src/eukalypse_now/static/admin/css/ie.css
src/eukalypse_now/static/admin/css/login.css
src/eukalypse_now/static/admin/css/rtl.css
src/eukalypse_now/static/admin/css/widgets.css
src/eukalypse_now/static/admin/img/changelist-bg.gif
src/eukalypse_now/static/admin/img/changelist-bg_rtl.gif
src/eukalypse_now/static/admin/img/chooser-bg.gif
src/eukalypse_now/static/admin/img/chooser_stacked-bg.gif
src/eukalypse_now/static/admin/img/default-bg-reverse.gif
src/eukalypse_now/static/admin/img/default-bg.gif
src/eukalypse_now/static/admin/img/deleted-overlay.gif
src/eukalypse_now/static/admin/img/icon-no.gif
src/eukalypse_now/static/admin/img/icon-unknown.gif
src/eukalypse_now/static/admin/img/icon-yes.gif
src/eukalypse_now/static/admin/img/icon_addlink.gif
