Metadata-Version: 1.1
Name: eukalypse-now
Version: 0.2
Summary: eukalypse web server
Home-page: UNKNOWN
Author: Dennis Schwertel
Author-email: s@digitalkultur.net
License: BSD
Platform: UNKNOWN
Classifier: Intended Audience :: Developers
Classifier: Intended Audience :: System Administrators
Classifier: Operating System :: OS Independent
Classifier: Topic :: Software Development
